<annotation>
  <folder></folder>
  <filename>Screenshot 2024-09-28 at 1.13.34PM.png</filename>
  <source>
    <database>Unknown</database>
    <annotation>Unknown</annotation>
    <image>Unknown</image>
  </source>
  <size>
    <width>502</width>
    <height>808</height>
    <depth></depth>
  </size>
  <segmented>0</segmented>
  <object>
    <name>Chicken</name>
    <truncated>0</truncated>
    <occluded>0</occluded>
    <difficult>0</difficult>
    <bndbox>
      <xmin>145.79</xmin>
      <ymin>500.08</ymin>
      <xmax>447.55999999999995</xmax>
      <ymax>746.56</ymax>
    </bndbox>
    <attributes>
      <attribute>
        <name>rotation</name>
        <value>0.0</value>
      </attribute>
    </attributes>
  </object>
  <object>
    <name>Chicken</name>
    <truncated>0</truncated>
    <occluded>0</occluded>
    <difficult>0</difficult>
    <bndbox>
      <xmin>83.8</xmin>
      <ymin>421.79</ymin>
      <xmax>421.46</xmax>
      <ymax>635.64</ymax>
    </bndbox>
    <attributes>
      <attribute>
        <name>rotation</name>
        <value>0.0</value>
      </attribute>
    </attributes>
  </object>
  <object>
    <name>Bacon</name>
    <truncated>0</truncated>
    <occluded>0</occluded>
    <difficult>0</difficult>
    <bndbox>
      <xmin>149.05</xmin>
      <ymin>110.39</ymin>
      <xmax>290.96</xmax>
      <ymax>252.3</ymax>
    </bndbox>
    <attributes>
      <attribute>
        <name>rotation</name>
        <value>0.0</value>
      </attribute>
    </attributes>
  </object>
  <object>
    <name>Bacon</name>
    <truncated>0</truncated>
    <occluded>0</occluded>
    <difficult>0</difficult>
    <bndbox>
      <xmin>222.45</xmin>
      <ymin>144.48</ymin>
      <xmax>374.15</xmax>
      <ymax>281.67</ymax>
    </bndbox>
    <attributes>
      <attribute>
        <name>rotation</name>
        <value>0.0</value>
      </attribute>
    </attributes>
  </object>
  <object>
    <name>Bacon</name>
    <truncated>0</truncated>
    <occluded>0</occluded>
    <difficult>0</difficult>
    <bndbox>
      <xmin>243.66</xmin>
      <ymin>20.67</ymin>
      <xmax>398.62</xmax>
      <ymax>182.16000000000003</ymax>
    </bndbox>
    <attributes>
      <attribute>
        <name>rotation</name>
        <value>0.0</value>
      </attribute>
    </attributes>
  </object>
  <object>
    <name>Bacon</name>
    <truncated>0</truncated>
    <occluded>0</occluded>
    <difficult>0</difficult>
    <bndbox>
      <xmin>178.41</xmin>
      <ymin>212.99</ymin>
      <xmax>292.59</xmax>
      <ymax>325.71</ymax>
    </bndbox>
    <attributes>
      <attribute>
        <name>rotation</name>
        <value>0.0</value>
      </attribute>
    </attributes>
  </object>
</annotation>
